discordsrv_api/__init__.py
discordsrv_api/models.py
discordsrv_api-0.2.6.dist-info/LICENSE
discordsrv_api-0.2.6.dist-info/METADATA
discordsrv_api-0.2.6.dist-info/WHEEL
discordsrv_api-0.2.6.dist-info/top_level.txt
discordsrv_api-0.2.6.dist-info/RECORD
