Metadata-Version: 2.1
Name: discordsrv-api
Version: 0.2.6
Summary: UUID to Discord ID converter for Minecraft and discordsrv
Home-page: https://git.cofob.ru/cofob/discordsrv_api
License: UNKNOWN
Platform: UNKNOWN
Requires-Python: >=3.6
License-File: LICENSE
Requires-Dist: mysql-connector-python
